sbol3/__init__.py
sbol3/attachment.py
sbol3/boolean_property.py
sbol3/builder_register.py
sbol3/collection.py
sbol3/combderiv.py
sbol3/component.py
sbol3/compref.py
sbol3/config.py
sbol3/constants.py
sbol3/constraint.py
sbol3/custom.py
sbol3/datetime_property.py
sbol3/document.py
sbol3/error.py
sbol3/expdata.py
sbol3/extdef.py
sbol3/feature.py
sbol3/float_property.py
sbol3/identified.py
sbol3/implementation.py
sbol3/int_property.py
sbol3/interaction.py
sbol3/interface.py
sbol3/localsub.py
sbol3/location.py
sbol3/model.py
sbol3/object.py
sbol3/om_compound.py
sbol3/om_prefix.py
sbol3/om_unit.py
sbol3/ownedobject.py
sbol3/participation.py
sbol3/property_base.py
sbol3/provenance.py
sbol3/refobj_property.py
sbol3/seqfeat.py
sbol3/sequence.py
sbol3/subcomponent.py
sbol3/text_property.py
sbol3/toplevel.py
sbol3/typing.py
sbol3/uri_property.py
sbol3/util.py
sbol3/utils.py
sbol3/validation.py
sbol3/varcomp.py
sbol3/rdf/sbol3-shapes.ttl
sbol3-1.2.0.post0.dist-info/LICENSE.txt
sbol3-1.2.0.post0.dist-info/METADATA
sbol3-1.2.0.post0.dist-info/WHEEL
sbol3-1.2.0.post0.dist-info/top_level.txt
sbol3-1.2.0.post0.dist-info/RECORD
